{"id":"map","title":"map","featureTypes":{"Default":{"style":{"nameLabel":"Name","drawingMode":"Point","strokeWidth":1,"strokeColor":"#0033ff","fillOpacity":1,"opacity":1,"fillColor":"#b0b09e","stroke":true,"rotate":0,"cornerRadius":50,"iconHeight":32,"iconWidth":32},"id":"api/resources/map#Default"}},"propertyTypeData":{"inwoners":{"title":"inwoners","type":"number","canEdit":false,"visibleInCallOut":true,"label":"inwoners","min":0,"max":1000,"section":"test"}},"propertyTypes":{},"url":"api/resources/map"}